dziner/__init__.py
dziner/agents.py
dziner/prompts.py
dziner/sascorer.py
dziner/tools.py
dziner/utils.py
dziner/version.py
dziner/sascorer_data/__init__.py
dziner/surrogates/__init__.py
dziner/surrogates/CMC/__init__.py
dziner/surrogates/CMC/model.py
dziner/surrogates/CO_2/__init__.py
dziner/surrogates/CO_2/inference_model.py
dziner/surrogates/CO_2/tokenizer/__init__.py
dziner/surrogates/CO_2/tokenizer/mof_tokenizer.py
dziner/surrogates/MOFormer/CO2_adsoption_training.py
dziner/surrogates/MOFormer/CO2_adsorption.py
dziner/surrogates/MOFormer/__init__.py
dziner/surrogates/MOFormer/finetune_cgcnn.py
dziner/surrogates/MOFormer/finetune_transformer.py
dziner/surrogates/MOFormer/tokenizer/__init__.py
dziner/surrogates/MOFormer/tokenizer/mof_tokenizer.py
dziner/surrogates/peptides/__init__.py
dziner/surrogates/solubility/__init__.py
dziner/surrogates/solubility/model.py
dziner-0.1.dist-info/LICENSE
dziner-0.1.dist-info/METADATA
dziner-0.1.dist-info/WHEEL
dziner-0.1.dist-info/dependency_links.txt
dziner-0.1.dist-info/top_level.txt
dziner-0.1.dist-info/RECORD
