Metadata-Version: 2.1
Name: dziner
Version: 0.1
Summary: Chemist AI Agent for Inverse Design of Materials with Natural Language Prompts
Home-page: https://github.com/mehradnas92/dziner
Author: Mehrad Ansari
Author-email: mehrad.ans@gmail.com
License: Apache-2.0
Keywords: dziner
Classifier: Development Status :: 2 - Pre-Alpha
Classifier: Intended Audience :: Developers
Classifier: License :: OSI Approved :: Apache Software License
Classifier: Natural Language :: English
Classifier: Programming Language :: Python :: 3.11
Requires-Python: >=3.9
License-File: LICENSE
Requires-Dist: langchain==0.1.16
Requires-Dist: langchain-openai==0.1.4
Requires-Dist: langchain-community==0.0.34
Requires-Dist: langchain-anthropic
Requires-Dist: openai==1.23.6
Requires-Dist: numpy==1.26.4
Requires-Dist: pandas==2.2.2
Requires-Dist: matplotlib==3.8.4
Requires-Dist: matplotlib-inline==0.1.7
Requires-Dist: scipy==1.13.0
Requires-Dist: transformers==4.40.2
Requires-Dist: PyYAML==6.0.1
Requires-Dist: google-search-results
Requires-Dist: pypdf
Requires-Dist: rdkit==2023.9.6
Requires-Dist: ipykernel
Requires-Dist: jupyter
Requires-Dist: tensorboard
Requires-Dist: pymatgen
Requires-Dist: dockstring
Requires-Dist: pytest
